AUTHORS
ChangeLog
LICENSE
README.rst
requirements.txt
setup.cfg
setup.py
etc/hapydeis
hapydeis/__init__.py
hapydeis/__main__.py
hapydeis/hapydeis.py
hapydeis.egg-info/PKG-INFO
hapydeis.egg-info/SOURCES.txt
hapydeis.egg-info/dependency_links.txt
hapydeis.egg-info/entry_points.txt
hapydeis.egg-info/not-zip-safe
hapydeis.egg-info/pbr.json
hapydeis.egg-info/requires.txt
hapydeis.egg-info/top_level.txt
tests/test_hapydeis.py