Metadata-Version: 1.1
Name: hapydeis
Version: 0.0.2.dev4
Summary: A python client for Deis clusters.
Home-page: UNKNOWN
Author: nassim.babaci
Author-email: nassim.babaci@cloudreach.com
License: UNKNOWN
Platform: UNKNOWN
Classifier: Development Status :: 4 - Beta
Classifier: Environment :: Console
Classifier: Intended Audience :: Developers
Classifier: Intended Audience :: Information Technology
Classifier: Operating System :: OS Independent
Classifier: Programming Language :: Python
